{"stats":{"minecraft:picked_up":{"minecraft:lead":4,"minecraft:seagrass":12,"aquaculture:blackfish":12,"minecraft:iron_chestplate":13,"minecraft:wheat":46,"croptopia:orange_juice":1,"minecraft:chainmail_boots":10,"minecraft:nether_brick_fence":9,"packedup:basicbackpack":2,"croptopia:kale":3,"croptopia:tomatillo_seed":2,"tombstone:tablet_of_home":1,"minecraft:diamond_sword":19,"minecraft:oak_stairs":5,"minecraft:enchanted_book":10,"minecraft:potion":2,"croptopia:cabbage_seed":4,"minecraft:stone_brick_stairs":40,"silentgear:fluffy_seeds":1,"minecraft:music_disc_cat":1,"silentgear:sinew":11,"minecraft:string":87,"croptopia:lettuce":1,"minecraft:raw_copper":12,"minecraft:red_nether_bricks":3,"minecraft:iron_leggings":10,"minecraft:pufferfish":14,"croptopia:hamburger":5,"minecraft:beetroot":1,"minecraft:diamond_leggings":2,"alexsmobs:blood_sac":1,"minecraft:gold_nugget":55,"minecraft:cobbled_deepslate":37,"minecraft:bucket":1,"minecraft:wooden_shovel":1,"minecraft:iron_pickaxe":6,"minecraft:smooth_quartz":6,"elementalcraft:inert_crystal":14,"minecraft:iron_boots":4,"minecraft:golden_helmet":2,"minecraft:tipped_arrow":52,"rootsclassic:whitecurrant":20,"minecraft:stick":116,"rootsclassic:verdant_sprig":1,"croptopia:cucumber":3,"croptopia:barley_seed":1,"potionsmaster:bezoar":5,"minecraft:torch":37,"minecraft:acacia_log":9,"supplementaries:bamboo_spikes_tipped":1,"minecraft:porkchop":4,"rootsclassic:nightshade":24,"aquaculture:atlantic_halibut":4,"tombstone:grave_dust":57,"minecraft:diorite":31,"elementalcraft:earth_shard":135,"minecraft:golden_chestplate":3,"minecraft:quartz_block":24,"minecraft:stone_sword":2,"minecraft:cactus":55,"minecraft:rotten_flesh":178,"minecraft:tropical_fish":3,"alexsmobs:capsid":1,"occultism:copper_ore":3,"occultism:datura":2,"aquaculture:neptunium_boots":3,"alltheores:silver_ingot":37,"minecraft:iron_bars":88,"minecraft:snowball":612,"minecraft:cobblestone":1061,"minecraft:cod":56,"croptopia:cabbage":3,"aquaculture:lockbox":1,"minecraft:nautilus_shell":2,"minecraft:birch_log":16,"minecraft:enchanting_table":2,"occultism:datura_seeds":4,"minecraft:leather_chestplate":4,"minecraft:feather":12,"minecraft:cooked_beef":1,"minecraft:iron_door":9,"cyclic:glass_connected":14,"minecraft:andesite":26,"minecraft:golden_leggings":3,"minecraft:smoker":1,"minecraft:potato":1,"ironchest:copper_chest":3,"minecraft:dirt":2968,"artifacts:flippers":1,"croptopia:toast_with_jam":1,"minecraft:polished_granite":9,"minecraft:leather_boots":10,"bhc:red_heart":37,"minecraft:glass":379,"alltheores:raw_tin":14,"minecraft:bone":399,"croptopia:rum":8,"croptopia:sweetpotato":1,"minecraft:bow":58,"minecraft:wheat_seeds":22,"minecraft:mossy_stone_bricks":24,"minecraft:diamond_helmet":2,"croptopia:kale_seed":5,"minecraft:oak_planks":80,"minecraft:mossy_stone_brick_stairs":2,"aquaculture:atlantic_herring":20,"aquaculture:jellyfish":6,"croptopia:chile_pepper_seed":2,"silentgear:fine_silk":2,"aquaculture:gar":2,"minecraft:cooked_porkchop":57,"elementalcraft:powerful_air_shard":2,"croptopia:mustard":1,"croptopia:celery_seed":1,"minecraft:sand":8195,"minecraft:nether_brick_stairs":2,"sophisticatedbackpacks:iron_backpack":1,"minecraft:ink_sac":4,"minecraft:grass_block":1,"minecraft:trapped_chest":1,"minecraft:chiseled_sandstone":1,"minecraft:mossy_cobblestone":19,"artifacts:plastic_drinking_hat":1,"minecraft:iron_hoe":4,"minecraft:polished_andesite":4,"rootsclassic:blackcurrant":22,"alexsmobs:guster_eye":1,"elementalcraft:air_shard":46,"minecraft:light_blue_terracotta":2,"croptopia:apple_pie":1,"minecraft:spruce_boat":3,"alltheores:raw_aluminum":2,"elementalcraft:powerful_earth_shard":7,"croptopia:tortilla":9,"minecraft:granite":49,"aquaculture:box":1,"minecraft:chainmail_helmet":7,"minecraft:bread":1,"alexsmobs:maggot":2,"minecraft:oak_sapling":151,"minecraft:netherrack":28,"minecraft:bricks":10,"elementalcraft:water_shard":42,"minecraft:diamond_pickaxe":3,"minecraft:fishing_rod":2,"minecraft:charcoal":2,"minecraft:azure_bluet":1,"minecraft:chicken":3,"croptopia:peach":3,"minecraft:leather_leggings":7,"croptopia:sweetpotato_seed":3,"rootsclassic:old_root":3,"minecraft:shield":11,"rootsclassic:elderberry":32,"appliedenergistics2:sky_stone_chest":1,"aquaculture:neptunium_helmet":2,"croptopia:saguaro_seed":6,"rootsclassic:redcurrant":24,"croptopia:blt":1,"minecraft:iron_axe":5,"artifacts:feral_claws":1,"minecraft:item_frame":1,"minecraft:iron_shovel":6,"aquaculture:pink_salmon":6,"minecraft:cracked_stone_bricks":20,"aquaculture:bluegill":4,"croptopia:tomatillo":1,"croptopia:tomato_seed":3,"minecraft:beef":12,"aquaculture:diamond_fishing_rod":1,"minecraft:oak_boat":6,"croptopia:pepper_seed":7,"minecraft:iron_nugget":3,"minecraft:poppy":4,"aquaculture:neptunium_chestplate":2,"minecraft:chest":3,"minecraft:birch_sapling":1,"minecraft:phantom_membrane":9,"minecraft:egg":11,"minecraft:raw_iron":6,"minecraft:sandstone":231,"minecraft:stone":1,"alltheores:raw_zinc":9,"aquaculture:driftwood":7,"aquaculture:perch":1,"minecraft:cookie":2,"minecraft:carrot":52,"aquaculture:neptunium_axe":1,"minecraft:stone_pressure_plate":9,"aquaculture:neptunium_leggings":2,"minecraft:polished_granite_stairs":1,"minecraft:arrow":314,"minecraft:diamond_chestplate":1,"minecraft:cooked_cod":27,"minecraft:beetroot_seeds":3,"minecraft:nether_bricks":3,"elementalcraft:powerful_water_shard":1,"aquaculture:brown_trout":1,"minecraft:diamond_boots":2,"aquaculture:carp":4,"tombstone:essence_of_undeath":1,"minecraft:saddle":2,"croptopia:pepper":5,"alltheores:raw_osmium":6,"minecraft:brick_stairs":2,"minecraft:mutton":9,"minecraft:white_wool":10,"aquaculture:tackle_box":5,"minecraft:salmon":28,"minecraft:leather":18,"aquaculture:neptunium_sword":1,"minecraft:cut_sandstone":2,"minecraft:birch_planks":26,"bhc:wither_bone":5,"aquaculture:neptunes_bounty":4,"minecraft:lily_pad":3,"minecraft:oak_log":884,"minecraft:chainmail_chestplate":10,"artifacts:superstitious_hat":1,"minecraft:golden_boots":2,"minecraft:gunpowder":31,"aquaculture:rainbow_trout":6,"minecraft:paper":9,"minecraft:orange_terracotta":1,"minecraft:cooked_mutton":7,"minecraft:red_carpet":3,"minecraft:red_nether_brick_stairs":3,"minecraft:kelp":6,"minecraft:apple":28,"minecraft:stone_bricks":183,"aquaculture:pacific_halibut":3,"minecraft:stone_pickaxe":1,"minecraft:cooked_chicken":6,"aquaculture:pollock":13,"croptopia:tomato":3,"aquaculture:minnow":5,"minecraft:glass_bottle":6,"minecraft:iron_sword":10,"minecraft:acacia_sapling":2,"minecraft:green_dye":21,"minecraft:book":40,"minecraft:chiseled_stone_bricks":2,"minecraft:quartz":13,"croptopia:cucumber_seed":6,"minecraft:gravel":7,"aquaculture:red_grouper":5,"minecraft:spruce_sapling":3,"minecraft:spruce_log":8,"minecraft:spider_eye":29,"croptopia:fried_chicken":1,"minecraft:leather_helmet":5,"aquaculture:atlantic_cod":3,"appliedenergistics2:sky_stone_block":41,"travelersbackpack:standard":1,"minecraft:diamond_shovel":3,"croptopia:saguaro":3,"xpbook:xp_tome":6,"minecraft:stone_axe":2,"elementalcraft:fire_shard":10,"aquaculture:neptunium_fishing_rod":1,"minecraft:chainmail_leggings":7,"croptopia:orange":10,"minecraft:iron_helmet":7,"appliedenergistics2:fluix_block":2,"minecraft:diamond_axe":1,"alltheores:raw_silver":11,"minecraft:mossy_cobblestone_stairs":6,"minecraft:baked_potato":1,"minecraft:coal":38,"minecraft:hopper":3,"minecraft:ender_pearl":2},"minecraft:broken":{"minecraft:golden_helmet":1,"minecraft:iron_shovel":2,"minecraft:iron_boots":1,"minecraft:iron_chestplate":2,"minecraft:iron_leggings":3,"minecraft:chainmail_boots":3,"minecraft:golden_leggings":1,"minecraft:chainmail_chestplate":1,"minecraft:stone_axe":2,"minecraft:iron_sword":1,"minecraft:diamond_sword":2,"minecraft:leather_helmet":1,"minecraft:stone_sword":1,"minecraft:diamond_leggings":1,"appliedenergistics2:nether_quartz_axe":1,"minecraft:chainmail_helmet":4,"minecraft:iron_axe":1,"minecraft:iron_pickaxe":1,"minecraft:iron_helmet":1},"minecraft:crafted":{"minecraft:oak_planks":928,"minecraft:birch_boat":1,"minecraft:cooked_chicken":8,"travelersbackpack:sleeping_bag":1,"minecraft:lever":1,"minecraft:diamond_shovel":4,"minecraft:cooked_mutton":36,"minecraft:green_dye":147,"minecraft:hopper":4,"aquaculture:neptunium_leggings":1,"minecraft:chest":18,"minecraft:oak_button":1,"packedup:basicbackpack":1,"minecraft:oak_fence":3,"minecraft:smoker":1,"minecraft:cooked_porkchop":23,"minecraft:crafting_table":5,"minecraft:spruce_planks":32,"travelersbackpack:standard":1,"minecraft:baked_potato":10,"minecraft:red_wool":2,"aquaculture:neptunium_axe":1,"minecraft:birch_planks":54,"aquaculture:neptunium_chestplate":1,"minecraft:book":2,"travelersbackpack:wolf":1,"minecraft:stick":4,"minecraft:iron_ingot":40,"minecraft:iron_block":13,"minecraft:redstone_torch":1,"minecraft:furnace":1,"minecraft:bone_meal":63,"minecraft:spruce_boat":1,"minecraft:cooked_beef":15,"minecraft:red_dye":2,"minecraft:cooked_cod":64,"ironchest:silver_chest":6,"travelersbackpack:backpack_tank":2,"cyclic:glass_connected":1,"ironchest:copper_chest":8,"minecraft:bucket":1,"minecraft:air":0,"minecraft:oak_boat":2,"minecraft:anvil":3,"minecraft:torch":128,"appliedenergistics2:nether_quartz_axe":1},"minecraft:mined":{"minecraft:oak_sapling":1,"croptopia:pepper_crop":2,"minecraft:white_bed":1,"minecraft:stone_pressure_plate":12,"occultism:copper_ore":3,"minecraft:red_nether_bricks":3,"minecraft:granite":48,"minecraft:acacia_log":9,"minecraft:grass_block":1246,"minecraft:hopper":3,"ironchest:copper_chest":3,"minecraft:chiseled_stone_bricks":2,"minecraft:spawner":102,"minecraft:mossy_cobblestone_stairs":6,"minecraft:red_nether_brick_stairs":2,"minecraft:iron_ore":6,"minecraft:fire":37,"minecraft:nether_brick_stairs":3,"minecraft:enchanting_table":1,"elementalcraft:inert_crystal_ore":14,"supplementaries:stick":1,"minecraft:oak_stairs":5,"minecraft:iron_bars":69,"minecraft:polished_granite_stairs":1,"minecraft:cut_sandstone":2,"minecraft:quartz_block":34,"minecraft:kelp_plant":1,"supplementaries:book_pile":6,"minecraft:smoker":1,"minecraft:orange_terracotta":1,"minecraft:torch":7,"minecraft:chest":2,"minecraft:poppy":4,"minecraft:dead_bush":1,"minecraft:white_stained_glass_pane":2,"minecraft:glass":352,"minecraft:nether_quartz_ore":13,"minecraft:cobblestone":75,"aquaculture:neptunes_bounty":2,"minecraft:oak_planks":122,"minecraft:bricks":10,"minecraft:iron_door":12,"minecraft:wall_torch":8,"appliedenergistics2:sky_stone_chest":1,"minecraft:birch_log":16,"minecraft:wheat":6,"alltheores:zinc_slate_ore":5,"alltheores:tin_ore":6,"cyclic:glass_connected":1,"minecraft:stone_brick_stairs":9,"minecraft:grass":46,"minecraft:oak_log":911,"minecraft:beetroots":1,"minecraft:dirt":2920,"alltheores:silver_nether_ore":4,"minecraft:sand":7172,"alltheores:osmium_nether_ore":1,"minecraft:netherrack":21,"minecraft:oak_leaves":33,"minecraft:deepslate":37,"minecraft:nether_gold_ore":14,"alltheores:osmium_slate_ore":5,"croptopia:cucumber_crop":2,"alltheores:tin_nether_ore":6,"alltheores:zinc_ore":4,"minecraft:mossy_cobblestone":12,"minecraft:nether_bricks":6,"minecraft:brick_stairs":2,"minecraft:spruce_leaves":3,"minecraft:kelp":1,"minecraft:sandstone":9,"minecraft:carrots":2,"aquaculture:tackle_box":5,"supplementaries:bamboo_spikes":1,"minecraft:chiseled_sandstone":1,"minecraft:snow":1744,"minecraft:andesite":24,"supplementaries:gunpowder":1,"minecraft:nether_brick_fence":8,"minecraft:mossy_stone_brick_stairs":4,"minecraft:bookshelf":11,"minecraft:vine":34,"alltheores:silver_ore":6,"alltheores:aluminum_ore":2,"minecraft:stone":409,"supplementaries:book_pile_horizontal":1,"minecraft:scaffolding":2,"minecraft:glass_pane":35,"minecraft:polished_granite":9,"silentgear:wild_fluffy_plant":1,"appliedenergistics2:fluix_block":2,"minecraft:copper_ore":4,"minecraft:tall_grass":11,"minecraft:diorite":31,"minecraft:birch_planks":1,"minecraft:cactus":31,"minecraft:ice":35,"minecraft:spruce_log":8,"minecraft:birch_leaves":5,"minecraft:coal_ore":1,"minecraft:cobweb":13,"croptopia:saguaro_crop":1,"minecraft:gravel":5,"appliedenergistics2:sky_stone_block":41,"minecraft:cracked_stone_bricks":13,"minecraft:polished_andesite":4,"minecraft:stone_bricks":29,"minecraft:mossy_stone_bricks":17},"minecraft:dropped":{"aquaculture:tackle_box":1,"sophisticatedbackpacks:iron_backpack":1,"occultism:datura_seeds":1,"minecraft:porkchop":2,"alltheores:raw_silver":1,"minecraft:lapis_lazuli":1,"minecraft:glass_bottle":8,"minecraft:ender_pearl":4,"minecraft:cooked_porkchop":15,"aquaculture:minnow":1,"minecraft:iron_horse_armor":1,"minecraft:cracked_stone_bricks":7,"minecraft:saddle":1,"xpbook:xp_tome":6,"croptopia:chile_pepper_seed":2,"aquaculture:neptunium_sword":1,"minecraft:cod":9,"croptopia:tomato_seed":1,"minecraft:dirt":153,"elementalcraft:water_shard":2,"aquaculture:neptunium_axe":1,"minecraft:cooked_cod":27,"croptopia:sweetpotato_seed":1,"minecraft:phantom_membrane":1,"minecraft:iron_pickaxe":2,"minecraft:white_wool":1,"minecraft:gold_ingot":6,"minecraft:bone":48,"minecraft:oak_planks":3,"minecraft:rotten_flesh":29,"minecraft:diamond_shovel":1,"minecraft:salmon":3,"minecraft:carrot":11,"minecraft:chainmail_chestplate":2,"minecraft:tipped_arrow":12,"aquaculture:bluegill":3,"minecraft:leather_leggings":1,"minecraft:iron_bars":5,"minecraft:arrow":44,"minecraft:glass":2367,"minecraft:netherrack":6,"minecraft:enchanting_table":1,"aquaculture:neptunium_leggings":2,"minecraft:enchanted_book":5,"minecraft:bread":1,"elementalcraft:fire_shard":1,"croptopia:lettuce_seed":1,"minecraft:wheat_seeds":3,"minecraft:golden_helmet":1,"minecraft:tnt":3,"cyclic:glass_connected":1,"minecraft:mossy_cobblestone":2,"tombstone:tablet_of_home":2,"minecraft:feather":1,"minecraft:cobblestone":354,"minecraft:book":14,"minecraft:granite":11,"minecraft:chainmail_helmet":2,"minecraft:grass_block":1,"minecraft:stick":9,"croptopia:celery_seed":1,"aquaculture:diamond_fishing_rod":1,"minecraft:diorite":1,"minecraft:ink_sac":4,"minecraft:green_dye":6,"tombstone:grave_key":1,"minecraft:smooth_quartz":3,"tombstone:grave_dust":18,"minecraft:iron_leggings":1,"aquaculture:neptunes_bounty":2,"minecraft:iron_axe":1,"minecraft:mossy_cobblestone_stairs":4,"biggerreactors:cyanite_ingot":26,"minecraft:string":4,"minecraft:lily_pad":3,"minecraft:spruce_sapling":3,"aquaculture:neptunium_fishing_rod":2,"packedup:basicbackpack":2,"elementalcraft:earth_shard":6,"minecraft:raw_copper":6,"minecraft:bowl":1,"minecraft:chicken":1,"minecraft:iron_boots":1,"minecraft:iron_hoe":1,"aquaculture:neptunium_boots":3,"minecraft:diamond_sword":5,"minecraft:shield":2,"minecraft:spruce_planks":23,"minecraft:diamond_pickaxe":2,"minecraft:iron_chestplate":2,"minecraft:andesite":10,"aquaculture:neptunium_chestplate":2,"minecraft:mossy_stone_bricks":3,"minecraft:oak_boat":2,"aquaculture:neptunium_helmet":2,"minecraft:spider_eye":4,"minecraft:diamond_boots":2,"minecraft:bow":3,"bhc:red_heart":4,"croptopia:pepper_seed":4,"minecraft:light_blue_terracotta":1},"minecraft:custom":{"minecraft:interact_with_crafting_table":65,"minecraft:open_barrel":6,"minecraft:bell_ring":1,"minecraft:eat_cake_slice":2,"minecraft:leave_game":17,"minecraft:time_since_death":191873,"minecraft:sprint_one_cm":3027573,"minecraft:damage_blocked_by_shield":8030,"minecraft:drop":283,"minecraft:talked_to_villager":1,"minecraft:play_time":1234320,"minecraft:deaths":13,"minecraft:jump":18991,"minecraft:walk_on_water_one_cm":355935,"minecraft:interact_with_furnace":111,"minecraft:sleep_in_bed":19,"minecraft:damage_dealt":112457,"minecraft:player_kills":1,"minecraft:crouch_one_cm":238209,"tombstone:undead_killed":457,"minecraft:interact_with_smoker":71,"minecraft:interact_with_smithing_table":1,"minecraft:horse_one_cm":384202,"minecraft:interact_with_anvil":49,"minecraft:mob_kills":690,"minecraft:inspect_hopper":59,"minecraft:items_inserted":18053,"minecraft:damage_dealt_resisted":3906,"minecraft:climb_one_cm":64905,"minecraft:walk_one_cm":2984941,"minecraft:damage_dealt_absorbed":120,"minecraft:sneak_time":79291,"minecraft:walk_under_water_one_cm":167590,"minecraft:interact_with_lectern":1,"minecraft:boat_one_cm":1135643,"minecraft:interact_with_blast_furnace":2,"minecraft:total_world_time":1234320,"tombstone:raider_killed":11,"minecraft:items_extracted":11098,"minecraft:interact_with_stonecutter":2,"minecraft:time_since_rest":10982,"minecraft:damage_taken":38638,"minecraft:damage_absorbed":78,"minecraft:trigger_trapped_chest":1,"minecraft:swim_one_cm":215859,"minecraft:fly_one_cm":3989960,"minecraft:open_chest":1079,"minecraft:fish_caught":208,"minecraft:fall_one_cm":607437},"minecraft:killed":{"minecraft:cave_spider":8,"minecraft:witch":1,"minecraft:spider":63,"alexsmobs:enderiophage":1,"alexsmobs:alligator_snapping_turtle":1,"minecraft:skeleton":174,"minecraft:bee":1,"minecraft:chicken":7,"minecraft:skeleton_horse":1,"artifacts:mimic":1,"minecraft:pig":16,"minecraft:zombie_villager":3,"minecraft:creeper":34,"alexsmobs:crimson_mosquito":2,"minecraft:sheep":10,"minecraft:zombie":154,"minecraft:stray":76,"minecraft:cow":6,"alexsmobs:tarantula_hawk":1,"alexsmobs:raccoon":1,"alexsmobs:rattlesnake":1,"minecraft:phantom":10,"minecraft:horse":2,"minecraft:llama":1,"minecraft:drowned":3,"alexsmobs:tusklin":2,"minecraft:husk":2,"alexsmobs:guster":1,"alexsmobs:cockroach":2,"alexsmobs:crow":1,"minecraft:wither_skeleton":34,"minecraft:enderman":2},"minecraft:killed_by":{"minecraft:wither_skeleton":1,"artifacts:mimic":1,"minecraft:zombie":2,"minecraft:player":3,"minecraft:skeleton":3,"minecraft:phantom":1},"minecraft:used":{"minecraft:polished_granite_stairs":1,"minecraft:iron_shovel":282,"minecraft:shield":184,"minecraft:chest":5,"minecraft:iron_sword":262,"minecraft:red_nether_brick_stairs":2,"rootsclassic:whitecurrant":3,"minecraft:nether_bricks":1,"minecraft:carrot":166,"appliedenergistics2:nether_quartz_axe":3,"rootsclassic:redcurrant":1,"minecraft:milk_bucket":1,"minecraft:snowball":128,"minecraft:glass":1981,"minecraft:spruce_boat":3,"minecraft:bricks":8,"minecraft:quartz_block":4,"minecraft:stone_bricks":88,"minecraft:item_frame":1,"aquaculture:neptunium_sword":1,"croptopia:peach":3,"minecraft:bow":489,"minecraft:oak_sapling":149,"minecraft:furnace":1,"croptopia:lettuce":1,"minecraft:cooked_cod":63,"supplementaries:bamboo_spikes_tipped":1,"minecraft:egg":5,"minecraft:potato":8,"rootsclassic:old_root":1,"croptopia:rum":14,"croptopia:orange_juice":2,"rootsclassic:elderberry":1,"minecraft:mossy_stone_bricks":6,"croptopia:tomato":3,"minecraft:stone_pickaxe":112,"minecraft:oak_planks":500,"minecraft:cactus":56,"cyclic:glass_connected":1,"minecraft:wooden_pickaxe":56,"minecraft:sandstone":9,"minecraft:diamond_axe":30,"minecraft:cookie":1,"croptopia:cucumber":3,"minecraft:golden_apple":2,"minecraft:white_wool":1,"minecraft:sand":76,"ironchest:copper_chest":5,"croptopia:hamburger":5,"croptopia:orange":10,"minecraft:redstone_torch":3,"minecraft:lever":3,"minecraft:chiseled_sandstone":1,"minecraft:melon_slice":2,"minecraft:bread":23,"minecraft:polished_granite":4,"croptopia:apple_pie":1,"minecraft:diamond_sword":2017,"croptopia:bellpepper":2,"minecraft:andesite":3,"minecraft:birch_log":2,"minecraft:oak_fence":1,"ironchest:silver_chest":6,"croptopia:cantaloupe":1,"minecraft:oak_boat":6,"minecraft:golden_pickaxe":3,"minecraft:iron_bars":31,"minecraft:stone_sword":7,"croptopia:toast_with_jam":1,"potionsmaster:bezoar":1,"croptopia:ham_sandwich":1,"minecraft:cooked_chicken":7,"minecraft:netherrack":2,"minecraft:torch":493,"minecraft:anvil":3,"minecraft:dirt":169,"minecraft:hopper":6,"aquaculture:neptunes_bounty":2,"croptopia:tortilla":9,"minecraft:granite":10,"alexsmobs:maggot":2,"minecraft:iron_axe":3,"minecraft:brick_stairs":2,"aquaculture:neptunium_fishing_rod":271,"minecraft:diamond_chestplate":1,"minecraft:cooked_beef":108,"minecraft:cooked_mutton":43,"minecraft:wheat_seeds":7,"aquaculture:tackle_box":4,"minecraft:water_bucket":104,"minecraft:birch_planks":73,"minecraft:bundle":1,"minecraft:polished_andesite":4,"minecraft:baked_potato":17,"minecraft:red_nether_bricks":1,"minecraft:birch_boat":1,"minecraft:cut_sandstone":2,"minecraft:cracked_stone_bricks":6,"minecraft:mossy_cobblestone":4,"minecraft:crafting_table":5,"minecraft:spider_eye":1,"croptopia:sweetpotato":1,"occultism:datura":2,"minecraft:smoker":1,"croptopia:kale":2,"aquaculture:neptunium_axe":5,"minecraft:diamond_pickaxe":950,"minecraft:apple":36,"minecraft:diamond_shovel":1360,"croptopia:cabbage":3,"minecraft:iron_pickaxe":251,"minecraft:stone_axe":88,"rootsclassic:nightshade":2,"minecraft:cobblestone":367,"minecraft:cooked_porkchop":75,"minecraft:potion":1,"croptopia:blt":1,"minecraft:bucket":105,"minecraft:glass_pane":93,"alexsmobs:animal_dictionary":3,"minecraft:diamond_leggings":1,"croptopia:honeydew":1}},"DataVersion":2730}